examples/advanced_app.py
examples/basic_app.py
flaskmcp/__init__.py
flaskmcp/app.py
flaskmcp/cli.py
flaskmcp/config.py
flaskmcp/schema.py
flaskmcp/context/__init__.py
flaskmcp/context/manager.py
flaskmcp/context/models.py
flaskmcp/core/__init__.py
flaskmcp/core/prompts.py
flaskmcp/core/resources.py
flaskmcp/core/tools.py
flaskmcp/docs/__init__.py
flaskmcp/docs/routes.py
flaskmcp/middleware/__init__.py
flaskmcp/middleware/auth.py
flaskmcp/middleware/error_handlers.py
flaskmcp/routes/__init__.py
flaskmcp/routes/prompts.py
flaskmcp/routes/resources.py
flaskmcp/routes/tools.py
flaskmcp/utils/__init__.py
flaskmcp/utils/helpers.py
flaskmcp-0.1.2.dist-info/licenses/LICENSE
tests/__init__.py
tests/test_prompts.py
tests/test_resources.py
tests/test_tools.py
flaskmcp-0.1.2.dist-info/METADATA
flaskmcp-0.1.2.dist-info/WHEEL
flaskmcp-0.1.2.dist-info/entry_points.txt
flaskmcp-0.1.2.dist-info/top_level.txt
flaskmcp-0.1.2.dist-info/RECORD
