Metadata-Version: 2.4
Name: flaskmcp
Version: 0.1.2
Summary: A Flask-based implementation of the Model Context Protocol (MCP)
Home-page: https://github.com/vprashant/flaskmcp
Author: Prashant Verma
Author-email: Prashant Verma <prashant27050@gmail.com>
License: MIT
Project-URL: Homepage, https://github.com/Vprashant/flaskmcp
Project-URL: Documentation, https://github.com/Vprashant/flaskmcp#readme
Project-URL: Repository, https://github.com/Vprashant/flaskmcp.git
Project-URL: Issues, https://github.com/Vprashant/flaskmcp/issues
Keywords: flask,mcp,llm,ai,model,context,protocol
Classifier: Development Status :: 4 - Beta
Classifier: Framework :: Flask
Classifier: Intended Audience :: Developers
Classifier: License :: OSI Approved :: MIT License
Classifier: Programming Language :: Python :: 3
Classifier: Programming Language :: Python :: 3.7
Classifier: Programming Language :: Python :: 3.8
Classifier: Programming Language :: Python :: 3.9
Classifier: Programming Language :: Python :: 3.10
Classifier: Programming Language :: Python :: 3.11
Classifier: Topic :: Software Development :: Libraries :: Application Frameworks
Classifier: Topic :: Software Development :: Libraries :: Python Modules
Requires-Python: >=3.7
License-File: LICENSE
Requires-Dist: Flask>=2.0.0
Requires-Dist: jsonschema>=4.0.0
Requires-Dist: werkzeug>=2.0.0
Provides-Extra: dev
Requires-Dist: pytest>=7.0.0; extra == "dev"
Requires-Dist: pytest-flask>=1.2.0; extra == "dev"
Requires-Dist: black>=23.0.0; extra == "dev"
Requires-Dist: isort>=5.10.0; extra == "dev"
Requires-Dist: flake8>=6.0.0; extra == "dev"
Provides-Extra: docs
Requires-Dist: sphinx>=4.0.0; extra == "docs"
Requires-Dist: sphinx-rtd-theme>=1.0.0; extra == "docs"
Dynamic: author
Dynamic: home-page
Dynamic: license-file
Dynamic: requires-python
